hello_universe/__init__.py
hello_universe/start.py
hello_universe-0.0.4.dist-info/LICENSE
hello_universe-0.0.4.dist-info/METADATA
hello_universe-0.0.4.dist-info/WHEEL
hello_universe-0.0.4.dist-info/top_level.txt
hello_universe-0.0.4.dist-info/RECORD
