Metadata-Version: 2.1
Name: hello-universe
Version: 0.0.4
Summary: A rookie pypi package to print Hello Universe
Home-page: https://github.com/jayanthvarma134/hello-universe
Author: M JAYANTH VARMA
Author-email: jayanthvarma134@gmail.com
License: UNKNOWN
Platform: UNKNOWN
Classifier: Programming Language :: Python :: 3
Classifier: License :: OSI Approved :: MIT License
Classifier: Operating System :: OS Independent
License-File: LICENSE
